CHANGELOG.txt
LICENSE.txt
MANIFEST.in
README.txt
setup.py
statistics.egg-info/PKG-INFO
statistics.egg-info/SOURCES.txt
statistics.egg-info/dependency_links.txt
statistics.egg-info/top_level.txt
stats/__init__.py