Metadata-Version: 2.1
Name: sean-stats
Version: 0.0.1
Summary: Some basic statistics functions
Home-page: UNKNOWN
Author: Sean Spitler
Author-email: midtree5784@gmail.com
License: MIT
Keywords: Statistics
Platform: UNKNOWN
Classifier: Development Status :: 5 - Production/Stable
Classifier: Intended Audience :: Education
Classifier: Operating System :: Microsoft :: Windows :: Windows 10
Classifier: License :: OSI Approved :: MIT License
Classifier: Programming Language :: Python :: 3
License-File: LICENSE.txt
